intelliops_sdk/__init__.py
intelliops_sdk/config.py
intelliops_sdk/module.py
intelliops_sdk/dto/__init__.py
intelliops_sdk/dto/error.py
intelliops_sdk-0.1.0.dist-info/LICENSE
intelliops_sdk-0.1.0.dist-info/METADATA
intelliops_sdk-0.1.0.dist-info/WHEEL
intelliops_sdk-0.1.0.dist-info/top_level.txt
intelliops_sdk-0.1.0.dist-info/RECORD
