Metadata-Version: 2.2
Name: intelliops-sdk
Version: 0.1.0
Summary: A Python SDK for IntelliOps
Home-page: https://github.com/yourusername/intelliops-sdk
Author: Kodez
Author-email: your.email@example.com
Classifier: Programming Language :: Python :: 3
Classifier: License :: OSI Approved :: MIT License
Classifier: Operating System :: OS Independent
Requires-Python: >=3.6
License-File: LICENSE
Requires-Dist: pydantic==2.10.6
Dynamic: author
Dynamic: author-email
Dynamic: classifier
Dynamic: description
Dynamic: description-content-type
Dynamic: home-page
Dynamic: requires-dist
Dynamic: requires-python
Dynamic: summary
